ges/__init__.py
ges/main.py
ges/utils.py
ges/scores/__init__.py
ges/scores/decomposable_score.py
ges/scores/gauss_obs_l0_pen.py
ges/test/__init__.py
ges/test/test_decomposable_score.py
ges/test/test_gauss_bic.py
ges/test/test_operators.py
ges/test/test_pdag_to_cpdag.py
ges/test/test_utils.py
ges/test/test_vs_pcalg.py
ges-1.1.1.dist-info/LICENSE.txt
ges-1.1.1.dist-info/METADATA
ges-1.1.1.dist-info/WHEEL
ges-1.1.1.dist-info/top_level.txt
ges-1.1.1.dist-info/RECORD
