Metadata-Version: 2.2
Name: ges
Version: 1.1.1
Summary: Python implementation of the GES algorithm for causal discovery
Home-page: https://github.com/juangamella/ges
Author: Juan L Gamella
Author-email: juangamella@gmail.com
License: BSD 3-Clause License
License-File: LICENSE.txt
Requires-Dist: numpy>=1.15.0
Dynamic: author
Dynamic: author-email
Dynamic: description
Dynamic: description-content-type
Dynamic: home-page
Dynamic: license
Dynamic: requires-dist
Dynamic: summary
